aliyunsdkgpdb/__init__.py
aliyunsdkgpdb/endpoint.py
aliyunsdkgpdb/request/__init__.py
aliyunsdkgpdb/request/v20160503/AllocateInstancePublicConnectionRequest.py
aliyunsdkgpdb/request/v20160503/CheckServiceLinkedRoleRequest.py
aliyunsdkgpdb/request/v20160503/CreateAccountRequest.py
aliyunsdkgpdb/request/v20160503/CreateCollectionRequest.py
aliyunsdkgpdb/request/v20160503/CreateDBInstancePlanRequest.py
aliyunsdkgpdb/request/v20160503/CreateDBInstanceRequest.py
aliyunsdkgpdb/request/v20160503/CreateNamespaceRequest.py
aliyunsdkgpdb/request/v20160503/CreateSampleDataRequest.py
aliyunsdkgpdb/request/v20160503/CreateServiceLinkedRoleRequest.py
aliyunsdkgpdb/request/v20160503/CreateVectorIndexRequest.py
aliyunsdkgpdb/request/v20160503/DeleteCollectionDataRequest.py
aliyunsdkgpdb/request/v20160503/DeleteCollectionRequest.py
aliyunsdkgpdb/request/v20160503/DeleteDBInstancePlanRequest.py
aliyunsdkgpdb/request/v20160503/DeleteDBInstanceRequest.py
aliyunsdkgpdb/request/v20160503/DeleteNamespaceRequest.py
aliyunsdkgpdb/request/v20160503/DeleteVectorIndexRequest.py
aliyunsdkgpdb/request/v20160503/DescribeAccountsRequest.py
aliyunsdkgpdb/request/v20160503/DescribeAvailableResourcesRequest.py
aliyunsdkgpdb/request/v20160503/DescribeBackupPolicyRequest.py
aliyunsdkgpdb/request/v20160503/DescribeCollectionRequest.py
aliyunsdkgpdb/request/v20160503/DescribeDBClusterNodeRequest.py
aliyunsdkgpdb/request/v20160503/DescribeDBClusterPerformanceRequest.py
aliyunsdkgpdb/request/v20160503/DescribeDBInstanceAttributeRequest.py
aliyunsdkgpdb/request/v20160503/DescribeDBInstanceDataBloatRequest.py
aliyunsdkgpdb/request/v20160503/DescribeDBInstanceDataSkewRequest.py
aliyunsdkgpdb/request/v20160503/DescribeDBInstanceDiagnosisSummaryRequest.py
aliyunsdkgpdb/request/v20160503/DescribeDBInstanceErrorLogRequest.py
aliyunsdkgpdb/request/v20160503/DescribeDBInstanceIPArrayListRequest.py
aliyunsdkgpdb/request/v20160503/DescribeDBInstanceIndexUsageRequest.py
aliyun_python_sdk_gpdb-1.1.7.dist-info/LICENSE
aliyun_python_sdk_gpdb-1.1.7.dist-info/METADATA
aliyun_python_sdk_gpdb-1.1.7.dist-info/WHEEL
aliyun_python_sdk_gpdb-1.1.7.dist-info/top_level.txt
aliyun_python_sdk_gpdb-1.1.7.dist-info/RECORD
